Workbook

Sheet Resumen
B2: CANCHA DE FUTBOL
B3: LIBRO DE TURNOS
B5: ENCARGADO | C5: =INGRESOS!C2 -> Elvis Herrera | I5: FECHA | J5: =INGRESOS!C3 -> 46118
C6: 1 | D6: 2 | E6: 3 | F6: 4 | G6: 5 | H6: 6 | I6: 7 | J6: TOTAL
B7: HORAS BASE | C7: =INGRESOS!J7 -> 0.041666667 | D7: =INGRESOS!J8 -> 0.069444444 | E7: =INGRESOS!J9 -> 0.083333333 | F7: =INGRESOS!J10 -> 0.041666667 | G7: =INGRESOS!J11 -> 0.041666667 | H7: =INGRESOS!J12 -> 0.069444444 | I7: =INGRESOS!J13 -> 0.048611111 | J7: =INGRESOS!M14 -> 19800
B8: EXTRAS HORAS LUZ | C8: =IF(ROUND(INGRESOS!N7,0)>0,"si","no") -> no | D8: =IF(ROUND(INGRESOS!N8,0)>0,"si","no") -> no | E8: =IF(ROUND(INGRESOS!N9,0)>0,"si","no") -> no | F8: =IF(ROUND(INGRESOS!N10,0)>0,"si","no") -> no | G8: =IF(ROUND(INGRESOS!N11,0)>0,"si","no") -> no | H8: =IF(ROUND(INGRESOS!N12,0)>0,"si","no") -> si | I8: =IF(ROUND(INGRESOS!N13,0)>0,"si","no") -> si | J8: =INGRESOS!N14 -> 320.5
B9: VESTUARIO | C9: =IF(INGRESOS!E7='Lista de Precios'!$C$6,"N",IF(INGRESOS!E7='Lista de Precios'!$D$6,"B",IF(INGRESOS!E7='Lista de Precios'!$E$6,"C",IF(INGRESOS!E7='Lista de Precios'!$F$6,"P","")))) -> N | D9: =IF(INGRESOS!E8='Lista de Precios'!$C$6,"N",IF(INGRESOS!E8='Lista de Precios'!$D$6,"B",IF(INGRESOS!E8='Lista de Precios'!$E$6,"C",IF(INGRESOS!E8='Lista de Precios'!$F$6,"P","")))) -> B | E9: =IF(INGRESOS!E9='Lista de Precios'!$C$6,"N",IF(INGRESOS!E9='Lista de Precios'!$D$6,"B",IF(INGRESOS!E9='Lista de Precios'!$E$6,"C",IF(INGRESOS!E9='Lista de Precios'!$F$6,"P","")))) -> C | F9: =IF(INGRESOS!E10='Lista de Precios'!$C$6,"N",IF(INGRESOS!E10='Lista de Precios'!$D$6,"B",IF(INGRESOS!E10='Lista de Precios'!$E$6,"C",IF(INGRESOS!E10='Lista de Precios'!$F$6,"P","")))) -> P | G9: =IF(INGRESOS!E11='Lista de Precios'!$C$6,"N",IF(INGRESOS!E11='Lista de Precios'!$D$6,"B",IF(INGRESOS!E11='Lista de Precios'!$E$6,"C",IF(INGRESOS!E11='Lista de Precios'!$F$6,"P","")))) -> B | H9: =IF(INGRESOS!E12='Lista de Precios'!$C$6,"N",IF(INGRESOS!E12='Lista de Precios'!$D$6,"B",IF(INGRESOS!E12='Lista de Precios'!$E$6,"C",IF(INGRESOS!E12='Lista de Precios'!$F$6,"P","")))) -> B | I9: =IF(INGRESOS!E13='Lista de Precios'!$C$6,"N",IF(INGRESOS!E13='Lista de Precios'!$D$6,"B",IF(INGRESOS!E13='Lista de Precios'!$E$6,"C",IF(INGRESOS!E13='Lista de Precios'!$F$6,"P","")))) -> N | J9: =INGRESOS!O14 -> 4890
B10: REFRIGERIO | C10: =IF(INGRESOS!F7='Lista de Precios'!$C$8,"N",IF(INGRESOS!F7='Lista de Precios'!$D$8,"M",IF(INGRESOS!F7='Lista de Precios'!$E$8,"B",IF(INGRESOS!F7='Lista de Precios'!$F$8,"A",IF(INGRESOS!F7='Lista de Precios'!$G$8,"C",""))))) -> B | D10: =IF(INGRESOS!F8='Lista de Precios'!$C$8,"N",IF(INGRESOS!F8='Lista de Precios'!$D$8,"M",IF(INGRESOS!F8='Lista de Precios'!$E$8,"B",IF(INGRESOS!F8='Lista de Precios'!$F$8,"A",IF(INGRESOS!F8='Lista de Precios'!$G$8,"C",""))))) -> M | E10: =IF(INGRESOS!F9='Lista de Precios'!$C$8,"N",IF(INGRESOS!F9='Lista de Precios'!$D$8,"M",IF(INGRESOS!F9='Lista de Precios'!$E$8,"B",IF(INGRESOS!F9='Lista de Precios'!$F$8,"A",IF(INGRESOS!F9='Lista de Precios'!$G$8,"C",""))))) -> N | F10: =IF(INGRESOS!F10='Lista de Precios'!$C$8,"N",IF(INGRESOS!F10='Lista de Precios'!$D$8,"M",IF(INGRESOS!F10='Lista de Precios'!$E$8,"B",IF(INGRESOS!F10='Lista de Precios'!$F$8,"A",IF(INGRESOS!F10='Lista de Precios'!$G$8,"C",""))))) -> B | G10: =IF(INGRESOS!F11='Lista de Precios'!$C$8,"N",IF(INGRESOS!F11='Lista de Precios'!$D$8,"M",IF(INGRESOS!F11='Lista de Precios'!$E$8,"B",IF(INGRESOS!F11='Lista de Precios'!$F$8,"A",IF(INGRESOS!F11='Lista de Precios'!$G$8,"C",""))))) -> B | H10: =IF(INGRESOS!F12='Lista de Precios'!$C$8,"N",IF(INGRESOS!F12='Lista de Precios'!$D$8,"M",IF(INGRESOS!F12='Lista de Precios'!$E$8,"B",IF(INGRESOS!F12='Lista de Precios'!$F$8,"A",IF(INGRESOS!F12='Lista de Precios'!$G$8,"C",""))))) -> N | I10: =IF(INGRESOS!F13='Lista de Precios'!$C$8,"N",IF(INGRESOS!F13='Lista de Precios'!$D$8,"M",IF(INGRESOS!F13='Lista de Precios'!$E$8,"B",IF(INGRESOS!F13='Lista de Precios'!$F$8,"A",IF(INGRESOS!F13='Lista de Precios'!$G$8,"C",""))))) -> M | J10: =INGRESOS!P14 -> 10790
B11: DESCUENTO | C11: =INGRESOS!Q7 -> 15 | D11: =INGRESOS!Q8 -> 15 | E11: =INGRESOS!Q9 -> 15 | F11: =INGRESOS!Q10 -> 15 | G11: =INGRESOS!Q11 -> 0 | H11: =INGRESOS!Q12 -> 0 | I11: =INGRESOS!Q13 -> 15 | J11: =INGRESOS!R14 -> 4674.075
B12: TOTAL INGRESOS | J12: =SUM(J7+J8+J9+J10-J11) -> 31126.425
B13: SALARIO | C13: =IF(INGRESOS!J22=1,'Lista de Precios'!C21,IF(INGRESOS!J22=2,'Lista de Precios'!E21,IF(INGRESOS!J22=3,'Lista de Precios'!D21,""))) -> 3200 | H13: REP_ REDES | J13: =IF(INGRESOS!J19=TRUE,'Lista de Precios'!C17,0) -> 100
B14: RIEGO DE CANCHA | C14: =IF(INGRESOS!J17=TRUE,'Lista de Precios'!C15,0) -> 160 | H14: INFLAR_B | J14: =IF(INGRESOS!J20=TRUE,'Lista de Precios'!C18,0) -> 70
B15: LIMPIEZA VESTUARIO | C15: =IF(INGRESOS!J18=TRUE,'Lista de Precios'!C16,0) -> 300
B16: TOTAL DE EGRESOS | J16: =C13+C14+C15+J13+J14 -> 3830
B18: OBSERVACIONES
B19: =INGRESOS!E18 -> se ha dañado la heladera se llamo al tecnico vendra mañana por la tarde
B25: DECLARACION
B26: ="El dia de hoy se generaron ingresos por un total de "&TEXT(J12,"$0,00.00")&", y egresos por un total de "&TEXT(J16,"$0,00.00")&". Por lo tanto el saldo final de el dia con fecha "&TEXT(J5,"dd/mm/yyyy")&" ha sido de "&TEXT( J12-J16,"$0,00.00") -> El dia de hoy se generaron ingresos por un total de $31,126.43, y egresos por un total de $3,830.00. Por lo tanto el saldo final de el dia con fecha 06/04/2026 ha sido de $27,296.43
B29: FIRMA

Sheet INGRESOS
B2: Encargado | C2: Elvis Herrera
B3: Fecha | C3: 46118
C5: Horario | E5: Extras
C6: Desde | D6: Hasta | E6: Vestuario | F6: Refrigerio | G6: Personas | I6: RESTA | J6: Final | K6: Horas | L6: Minutos | M6: Totales | N6: Extra luz | O6: Vestuario | P6: Refrigerio | Q6: Descuento % | R6: Descuento $
B7: Turno 1 | C7: 0.375 | D7: 0.41666667 | E7: No | F7: Bàsico | G7: 40 | I7: 0.041666667 | J7: =IF(HOUR(I7)<1,_xlfn.CEILING.MATH(I7,"01:00"),_xlfn.CEILING.MATH(I7,"00:10")) -> 0.041666667 | K7: =HOUR(J7) -> 1 | L7: =MINUTE(J7)/10 -> 0 | M7: =((K7*'Lista de Precios'!$C$5)+(L7*'Lista de Precios'!$E$5))*G7 -> 4000 | N7: =IF(C7>0.75,((K7*'Lista de Precios'!$D$5)+(L7*'Lista de Precios'!$F$5))*G7,"0") -> 0 | O7: =IF(INGRESOS!E7='Lista de Precios'!$C$6,'Lista de Precios'!$C$7,IF(E7='Lista de Precios'!$D$6,'Lista de Precios'!$D$7,IF(E7='Lista de Precios'!$E$6,'Lista de Precios'!$E$7,IF(E7='Lista de Precios'!$F$6,'Lista de Precios'!$F$7,0))))*G7 -> 0 | P7: =IF(F7='Lista de Precios'!$C$8,'Lista de Precios'!$C$9,IF(F7='Lista de Precios'!$D$8,'Lista de Precios'!$D$9,IF(F7='Lista de Precios'!$E$8,'Lista de Precios'!$E$9,IF(F7='Lista de Precios'!$F$8,'Lista de Precios'!$F$9,IF(F7='Lista de Precios'!$G$8,'Lista de Precios'!$G$9,0)))))*G7 -> 4400 | Q7: =IF(G7<=10,'Lista de Precios'!$C$11,IF(INGRESOS!G7<=15,'Lista de Precios'!$D$11,'Lista de Precios'!$E$11)) -> 15 | R7: =SUM(M7+N7+O7+P7)*Q7/100 -> 1260
B8: Turno 2 | C8: 0.4375 | D8: 0.50069444 | E8: Bàsico | F8: Minimo | G8: 19 | I8: =D8-C8 -> 0.063194444 | J8: =IF(HOUR(I8)<1,_xlfn.CEILING.MATH(I8,"01:00"),_xlfn.CEILING.MATH(I8,"00:10")) -> 0.069444444 | K8: =HOUR(J8) -> 1 | L8: =MINUTE(J8)/10 -> 4 | M8: =((K8*'Lista de Precios'!$C$5)+(L8*'Lista de Precios'!$E$5))*G8 -> 3420 | N8: =IF(C8>0.75,((K8*'Lista de Precios'!$D$5)+(L8*'Lista de Precios'!$F$5))*G8,"0") -> 0 | O8: =IF(INGRESOS!E8='Lista de Precios'!$C$6,'Lista de Precios'!$C$7,IF(E8='Lista de Precios'!$D$6,'Lista de Precios'!$D$7,IF(E8='Lista de Precios'!$E$6,'Lista de Precios'!$E$7,IF(E8='Lista de Precios'!$F$6,'Lista de Precios'!$F$7,0))))*G8 -> 570 | P8: =IF(F8='Lista de Precios'!$C$8,'Lista de Precios'!$C$9,IF(F8='Lista de Precios'!$D$8,'Lista de Precios'!$D$9,IF(F8='Lista de Precios'!$E$8,'Lista de Precios'!$E$9,IF(F8='Lista de Precios'!$F$8,'Lista de Precios'!$F$9,IF(F8='Lista de Precios'!$G$8,'Lista de Precios'!$G$9,0)))))*G8 -> 1710 | Q8: =IF(G8<=10,'Lista de Precios'!$C$11,IF(INGRESOS!G8<=15,'Lista de Precios'!$D$11,'Lista de Precios'!$E$11)) -> 15 | R8: =SUM(M8+N8+O8+P8)*Q8/100 -> 855
B9: Turno 3 | C9: 0.51041667 | D9: 0.59166667 | E9: Confort | F9: No | G9: 28 | I9: =D9-C9 -> 0.08125 | J9: =IF(HOUR(I9)<1,_xlfn.CEILING.MATH(I9,"01:00"),_xlfn.CEILING.MATH(I9,"00:10")) -> 0.083333333 | K9: =HOUR(J9) -> 2 | L9: =MINUTE(J9)/10 -> 0 | M9: =((K9*'Lista de Precios'!$C$5)+(L9*'Lista de Precios'!$E$5))*G9 -> 5600 | N9: =IF(C9>0.75,((K9*'Lista de Precios'!$D$5)+(L9*'Lista de Precios'!$F$5))*G9,"0") -> 0 | O9: =IF(INGRESOS!E9='Lista de Precios'!$C$6,'Lista de Precios'!$C$7,IF(E9='Lista de Precios'!$D$6,'Lista de Precios'!$D$7,IF(E9='Lista de Precios'!$E$6,'Lista de Precios'!$E$7,IF(E9='Lista de Precios'!$F$6,'Lista de Precios'!$F$7,0))))*G9 -> 1680 | P9: =IF(F9='Lista de Precios'!$C$8,'Lista de Precios'!$C$9,IF(F9='Lista de Precios'!$D$8,'Lista de Precios'!$D$9,IF(F9='Lista de Precios'!$E$8,'Lista de Precios'!$E$9,IF(F9='Lista de Precios'!$F$8,'Lista de Precios'!$F$9,IF(F9='Lista de Precios'!$G$8,'Lista de Precios'!$G$9,0)))))*G9 -> 0 | Q9: =IF(G9<=10,'Lista de Precios'!$C$11,IF(INGRESOS!G9<=15,'Lista de Precios'!$D$11,'Lista de Precios'!$E$11)) -> 15 | R9: =SUM(M9+N9+O9+P9)*Q9/100 -> 1092
B10: Turno 4 | C10: 0.625 | D10: 0.66527778 | E10: Premium | F10: Bàsico | G10: 17 | I10: =D10-C10 -> 0.040277778 | J10: =IF(HOUR(I10)<1,_xlfn.CEILING.MATH(I10,"01:00"),_xlfn.CEILING.MATH(I10,"00:10")) -> 0.041666667 | K10: =HOUR(J10) -> 1 | L10: =MINUTE(J10)/10 -> 0 | M10: =((K10*'Lista de Precios'!$C$5)+(L10*'Lista de Precios'!$E$5))*G10 -> 1700 | N10: =IF(C10>0.75,((K10*'Lista de Precios'!$D$5)+(L10*'Lista de Precios'!$F$5))*G10,"0") -> 0 | O10: =IF(INGRESOS!E10='Lista de Precios'!$C$6,'Lista de Precios'!$C$7,IF(E10='Lista de Precios'!$D$6,'Lista de Precios'!$D$7,IF(E10='Lista de Precios'!$E$6,'Lista de Precios'!$E$7,IF(E10='Lista de Precios'!$F$6,'Lista de Precios'!$F$7,0))))*G10 -> 2040 | P10: =IF(F10='Lista de Precios'!$C$8,'Lista de Precios'!$C$9,IF(F10='Lista de Precios'!$D$8,'Lista de Precios'!$D$9,IF(F10='Lista de Precios'!$E$8,'Lista de Precios'!$E$9,IF(F10='Lista de Precios'!$F$8,'Lista de Precios'!$F$9,IF(F10='Lista de Precios'!$G$8,'Lista de Precios'!$G$9,0)))))*G10 -> 1870 | Q10: =IF(G10<=10,'Lista de Precios'!$C$11,IF(INGRESOS!G10<=15,'Lista de Precios'!$D$11,'Lista de Precios'!$E$11)) -> 15 | R10: =SUM(M10+N10+O10+P10)*Q10/100 -> 841.5
B11: Turno 5 | C11: 0.72222222 | D11: 0.73819444 | E11: Bàsico | F11: Bàsico | G11: 10 | I11: =D11-C11 -> 0.015972222 | J11: =IF(HOUR(I11)<1,_xlfn.CEILING.MATH(I11,"01:00"),_xlfn.CEILING.MATH(I11,"00:10")) -> 0.041666667 | K11: =HOUR(J11) -> 1 | L11: =MINUTE(J11)/10 -> 0 | M11: =((K11*'Lista de Precios'!$C$5)+(L11*'Lista de Precios'!$E$5))*G11 -> 1000 | N11: =IF(C11>0.75,((K11*'Lista de Precios'!$D$5)+(L11*'Lista de Precios'!$F$5))*G11,"0") -> 0 | O11: =IF(INGRESOS!E11='Lista de Precios'!$C$6,'Lista de Precios'!$C$7,IF(E11='Lista de Precios'!$D$6,'Lista de Precios'!$D$7,IF(E11='Lista de Precios'!$E$6,'Lista de Precios'!$E$7,IF(E11='Lista de Precios'!$F$6,'Lista de Precios'!$F$7,0))))*G11 -> 300 | P11: =IF(F11='Lista de Precios'!$C$8,'Lista de Precios'!$C$9,IF(F11='Lista de Precios'!$D$8,'Lista de Precios'!$D$9,IF(F11='Lista de Precios'!$E$8,'Lista de Precios'!$E$9,IF(F11='Lista de Precios'!$F$8,'Lista de Precios'!$F$9,IF(F11='Lista de Precios'!$G$8,'Lista de Precios'!$G$9,0)))))*G11 -> 1100 | Q11: =IF(G11<=10,'Lista de Precios'!$C$11,IF(INGRESOS!G11<=15,'Lista de Precios'!$D$11,'Lista de Precios'!$E$11)) -> 0 | R11: =SUM(M11+N11+O11+P11)*Q11/100 -> 0
B12: Turno 6 | C12: 0.80555556 | D12: 0.86944444 | E12: Bàsico | F12: No | G12: 10 | I12: =D12-C12 -> 0.063888889 | J12: =IF(HOUR(I12)<1,_xlfn.CEILING.MATH(I12,"01:00"),_xlfn.CEILING.MATH(I12,"00:10")) -> 0.069444444 | K12: =HOUR(J12) -> 1 | L12: =MINUTE(J12)/10 -> 4 | M12: =((K12*'Lista de Precios'!$C$5)+(L12*'Lista de Precios'!$E$5))*G12 -> 1800 | N12: =IF(C12>0.75,((K12*'Lista de Precios'!$D$5)+(L12*'Lista de Precios'!$F$5))*G12,"0") -> 140 | O12: =IF(INGRESOS!E12='Lista de Precios'!$C$6,'Lista de Precios'!$C$7,IF(E12='Lista de Precios'!$D$6,'Lista de Precios'!$D$7,IF(E12='Lista de Precios'!$E$6,'Lista de Precios'!$E$7,IF(E12='Lista de Precios'!$F$6,'Lista de Precios'!$F$7,0))))*G12 -> 300 | P12: =IF(F12='Lista de Precios'!$C$8,'Lista de Precios'!$C$9,IF(F12='Lista de Precios'!$D$8,'Lista de Precios'!$D$9,IF(F12='Lista de Precios'!$E$8,'Lista de Precios'!$E$9,IF(F12='Lista de Precios'!$F$8,'Lista de Precios'!$F$9,IF(F12='Lista de Precios'!$G$8,'Lista de Precios'!$G$9,0)))))*G12 -> 0 | Q12: =IF(G12<=10,'Lista de Precios'!$C$11,IF(INGRESOS!G12<=15,'Lista de Precios'!$D$11,'Lista de Precios'!$E$11)) -> 0 | R12: =SUM(M12+N12+O12+P12)*Q12/100 -> 0
B13: Turno 7 | C13: 0.88541667 | D13: 0.92847222 | E13: No | F13: Minimo | G13: 19 | I13: =D13-C13 -> 0.043055556 | J13: =IF(HOUR(I13)<1,_xlfn.CEILING.MATH(I13,"01:00"),_xlfn.CEILING.MATH(I13,"00:10")) -> 0.048611111 | K13: =HOUR(J13) -> 1 | L13: =MINUTE(J13)/10 -> 1 | M13: =((K13*'Lista de Precios'!$C$5)+(L13*'Lista de Precios'!$E$5))*G13 -> 2280 | N13: =IF(C13>0.75,((K13*'Lista de Precios'!$D$5)+(L13*'Lista de Precios'!$F$5))*G13,"0") -> 180.5 | O13: =IF(INGRESOS!E13='Lista de Precios'!$C$6,'Lista de Precios'!$C$7,IF(E13='Lista de Precios'!$D$6,'Lista de Precios'!$D$7,IF(E13='Lista de Precios'!$E$6,'Lista de Precios'!$E$7,IF(E13='Lista de Precios'!$F$6,'Lista de Precios'!$F$7,0))))*G13 -> 0 | P13: =IF(F13='Lista de Precios'!$C$8,'Lista de Precios'!$C$9,IF(F13='Lista de Precios'!$D$8,'Lista de Precios'!$D$9,IF(F13='Lista de Precios'!$E$8,'Lista de Precios'!$E$9,IF(F13='Lista de Precios'!$F$8,'Lista de Precios'!$F$9,IF(F13='Lista de Precios'!$G$8,'Lista de Precios'!$G$9,0)))))*G13 -> 1710 | Q13: =IF(G13<=10,'Lista de Precios'!$C$11,IF(INGRESOS!G13<=15,'Lista de Precios'!$D$11,'Lista de Precios'!$E$11)) -> 15 | R13: =SUM(M13+N13+O13+P13)*Q13/100 -> 625.575
I14: =SUM(I7:I13) -> 0.34930556 | J14: =SUM(J7:J13) -> 0.39583333 | K14: =SUM(K7:K13) -> 8 | L14: =SUM(L7:L13) -> 9 | M14: =SUM(M7:M13) -> 19800 | N14: =SUM(N12:N13) -> 320.5 | O14: =SUM(O7:O13) -> 4890 | P14: =SUM(P7:P13) -> 10790 | R14: =SUM(R7:R13) -> 4674.075
B15: Adicionales Diarios
I17: Riego | J17: TRUE
E18: se ha dañado la heladera se llamo al tecnico vendra mañana por la tarde | I18: Limpieza | J18: TRUE
I19: Redes | J19: TRUE
I20: Pelotas | J20: TRUE
I21: Jornada | J21: 2
I22: Domingo | J22: =IF(WEEKDAY(C3)=1,3,J21) -> 2

Sheet Lista de Precios
B2: INGRESOS
B4: Horas Cancha | C4: Diurno | D4: Nocturno | E4: Hora fraccion | F4: Luz fraccion
C5: 100 | D5: 8 | E5: 20 | F5: 1.5
B6: Vestuario | C6: No | D6: Bàsico | E6: Confort | F6: Premium
C7: 0 | D7: 30 | E7: 60 | F7: 120
B8: Refrigerio | C8: No | D8: Minimo | E8: Bàsico | F8: Abundante | G8: Completo
C9: 0 | D9: 90 | E9: 110 | F9: 130 | G9: 185
B10: Descuentos | C10: 1 a 10 | D10: 11 a 15 | E10: 16 o +
C11: 0 | D11: 10 | E11: 15
B13: COSTOS
B15: Riego de Cancha | C15: 160
B16: Limpieza de Vestuarios | C16: 300
B17: Reparacion de Redes | C17: 100
B18: Inflar Pelotas | C18: 70
B20: Descuentos | C20: Normal | D20: Domingo | E20: Feriado
C21: 1600 | D21: 2200 | E21: 3200
